README.md
setup.py
albertk/AutoEncoder.py
albertk/__init__.py
albertk/fun.py
albertk.egg-info/PKG-INFO
albertk.egg-info/SOURCES.txt
albertk.egg-info/dependency_links.txt
albertk.egg-info/requires.txt
albertk.egg-info/top_level.txt