Metadata-Version: 2.1
Name: albertk
Version: 0.0.1.32
Summary: Terry albertk
Home-page: https://terry-toolkit.terrychan.org/zh/master/
Author: Terry Chan
Author-email: napoler2008@gmail.com
License: UNKNOWN
Platform: UNKNOWN
